[
  {
    "id": 1,
    "fullName": "Amelia Johnson",
    "dateOfBirth": "1984-07-12",
    "gender": "Female",
    "phone": "+1 (215) 555-0110",
    "address": "312 Maple Street, Philadelphia, PA",
    "doctorId": 1
  },
  {
    "id": 2,
    "fullName": "Luis Ramirez",
    "dateOfBirth": "1971-11-04",
    "gender": "Male",
    "phone": "+1 (215) 555-0147",
    "address": "19 Elm Avenue, Philadelphia, PA",
    "doctorId": 1
  },
  {
    "id": 3,
    "fullName": "Nora Williams",
    "dateOfBirth": "1990-05-28",
    "gender": "Female",
    "phone": "+1 (215) 555-0163",
    "address": "740 Oak Lane, Upper Darby, PA",
    "doctorId": 3
  },
  {
    "id": 4,
    "fullName": "Ethan Foster",
    "dateOfBirth": "2014-10-19",
    "gender": "Male",
    "phone": "+1 (215) 555-0194",
    "address": "1826 Cedar Street, Lansdowne, PA",
    "doctorId": 5
  },
  {
    "id": 5,
    "fullName": "Maya Simmons",
    "dateOfBirth": "2007-08-03",
    "gender": "Female",
    "phone": "+1 (215) 555-0138",
    "address": "21 Birch Road, Havertown, PA",
    "doctorId": 5
  },
  {
    "id": 6,
    "fullName": "Noah Greene",
    "dateOfBirth": "1963-01-27",
    "gender": "Male",
    "phone": "+1 (215) 555-0171",
    "address": "584 Pine Street, Chester, PA",
    "doctorId": 2
  },
  {
    "id": 7,
    "fullName": "Zoe Carter",
    "dateOfBirth": "1998-12-15",
    "gender": "Female",
    "phone": "+1 (215) 555-0185",
    "address": "907 Walnut Avenue, Media, PA",
    "doctorId": 6
  },
  {
    "id": 8,
    "fullName": "Caleb Turner",
    "dateOfBirth": "1958-06-21",
    "gender": "Male",
    "phone": "+1 (215) 555-0116",
    "address": "434 Spruce Drive, Drexel Hill, PA",
    "doctorId": 7
  },
  {
    "id": 9,
    "fullName": "Iris Nguyen",
    "dateOfBirth": "1989-02-11",
    "gender": "Female",
    "phone": "+1 (215) 555-0189",
    "address": "1250 Ridge Road, Broomall, PA",
    "doctorId": 2
  },
  {
    "id": 10,
    "fullName": "Sofia Patel",
    "dateOfBirth": "1994-03-30",
    "gender": "Female",
    "phone": "+1 (215) 555-0128",
    "address": "2906 Forest Avenue, Philadelphia, PA",
    "doctorId": 8
  },
  {
    "id": 11,
    "fullName": "Logan Blake",
    "dateOfBirth": "2017-06-07",
    "gender": "Male",
    "phone": "+1 (215) 555-0154",
    "address": "412 Spruce Place, Norristown, PA",
    "doctorId": 5
  },
  {
    "id": 12,
    "fullName": "Hannah Ellis",
    "dateOfBirth": "1978-09-18",
    "gender": "Female",
    "phone": "+1 (215) 555-0141",
    "address": "674 Hazel Street, Philadelphia, PA",
    "doctorId": 9
  },
  {
    "id": 13,
    "fullName": "Jackson Ward",
    "dateOfBirth": "1986-04-09",
    "gender": "Male",
    "phone": "+1 (215) 555-0176",
    "address": "118 Oakwood Terrace, Ardmore, PA",
    "doctorId": 10
  },
  {
    "id": 14,
    "fullName": "Leila Morgan",
    "dateOfBirth": "1954-11-29",
    "gender": "Female",
    "phone": "+1 (215) 555-0160",
    "address": "831 Cherry Street, Collingdale, PA",
    "doctorId": 1
  },
  {
    "id": 15,
    "fullName": "Owen Bennett",
    "dateOfBirth": "2001-01-13",
    "gender": "Male",
    "phone": "+1 (215) 555-0145",
    "address": "223 Linden Avenue, Springfield, PA",
    "doctorId": 3
  },
  {
    "id": 16,
    "fullName": "Samantha Ortiz",
    "dateOfBirth": "1982-05-02",
    "gender": "Female",
    "phone": "+1 (215) 555-0118",
    "address": "955 Magnolia Drive, Upper Darby, PA",
    "doctorId": 4
  },
  {
    "id": 17,
    "fullName": "Amir Hassan",
    "dateOfBirth": "1973-08-24",
    "gender": "Male",
    "phone": "+1 (215) 555-0191",
    "address": "50 Willow Lane, Sharon Hill, PA",
    "doctorId": 2
  },
  {
    "id": 18,
    "fullName": "Grace Thompson",
    "dateOfBirth": "1991-02-05",
    "gender": "Female",
    "phone": "+1 (215) 555-0182",
    "address": "361 Juniper Street, Norwood, PA",
    "doctorId": 6
  },
  {
    "id": 19,
    "fullName": "Noelle Parker",
    "dateOfBirth": "2005-12-22",
    "gender": "Female",
    "phone": "+1 (215) 555-0157",
    "address": "207 Aspen Court, Havertown, PA",
    "doctorId": 7
  },
  {
    "id": 20,
    "fullName": "Rafael Gomez",
    "dateOfBirth": "1968-03-08",
    "gender": "Male",
    "phone": "+1 (215) 555-0130",
    "address": "980 Spruce Street, Philadelphia, PA",
    "doctorId": 9
  },
  {
    "id": 21,
    "fullName": "Anna Chen",
    "dateOfBirth": "2001-08-05",
    "gender": "Female",
    "phone": "9876543456789",
    "address": "USA",
    "doctorId": 3
  }
]
